ods_exd_api_box/__init__.py
ods_exd_api_box/exceptions.py
ods_exd_api_box/external_data_reader.py
ods_exd_api_box/file_handler_registry.py
ods_exd_api_box/file_interface.py
ods_exd_api_box/py.typed
ods_exd_api_box/server.py
ods_exd_api_box/proto/.update_stubs.sh
ods_exd_api_box/proto/__init__.py
ods_exd_api_box/proto/ods_external_data_pb2.py
ods_exd_api_box/proto/ods_external_data_pb2.pyi
ods_exd_api_box/proto/ods_external_data_pb2_grpc.py
ods_exd_api_box/proto/ods_pb2.py
ods_exd_api_box/proto/ods_pb2.pyi
ods_exd_api_box/proto/ods_pb2_grpc.py
ods_exd_api_box/proto/py.typed
ods_exd_api_box/simple/__init__.py
ods_exd_api_box/simple/file_simple.py
ods_exd_api_box/simple/file_simple_interface.py
ods_exd_api_box/utils/__init__.py
ods_exd_api_box/utils/attribute_helper.py
ods_exd_api_box/utils/param_parser.py
ods_exd_api_box/utils/time_helper.py
ods_exd_api_box-1.3.0.dist-info/licenses/LICENSE
ods_exd_api_box-1.3.0.dist-info/METADATA
ods_exd_api_box-1.3.0.dist-info/WHEEL
ods_exd_api_box-1.3.0.dist-info/top_level.txt
ods_exd_api_box-1.3.0.dist-info/RECORD
