Metadata-Version: 2.4
Name: ods-exd-api-box
Version: 1.3.0
Summary: Helper package to build ASAM ODS EXD API grpc plugins.
Author-email: Andreas K <totonga@gmail.com>
License: MIT
Project-URL: Homepage, https://github.com/totonga/ods-exd-api-box
Project-URL: Documentation, https://github.com/totonga/ods-exd-api-box/tree/main#readme
Project-URL: Repository, https://github.com/totonga/ods-exd-api-box
Project-URL: Tracker, https://github.com/totonga/ods-exd-api-box/issues
Project-URL: Changelog, https://github.com/totonga/ods-exd-api-box/blob/main/CHANGELOG.md
Keywords: asam,ods,grpc,plugin,data analysis
Classifier: Development Status :: 3 - Alpha
Classifier: Intended Audience :: Science/Research
Classifier: License :: OSI Approved :: MIT License
Classifier: Operating System :: OS Independent
Classifier: Programming Language :: Python :: 3
Classifier: Programming Language :: Python :: 3.12
Classifier: Topic :: Software Development :: Libraries :: Python Modules
Classifier: Topic :: Scientific/Engineering :: Information Analysis
Requires-Python: >=3.12
License-File: LICENSE
Requires-Dist: grpcio<2.0.0,>=1.76.0
Requires-Dist: grpcio-health-checking<2.0.0,>=1.76.0
Requires-Dist: grpcio-tools<2.0.0,>=1.76.0
Provides-Extra: dev
Requires-Dist: build>=1.4.0; extra == "dev"
Requires-Dist: coverage>=7.0; extra == "dev"
Requires-Dist: isort>=5.12; extra == "dev"
Requires-Dist: black>=25.12.0; extra == "dev"
Requires-Dist: mypy>=1.5; extra == "dev"
Requires-Dist: types-protobuf>=4.0; extra == "dev"
Requires-Dist: types-grpcio>=1; extra == "dev"
Requires-Dist: types-grpcio-health-checking>=1; extra == "dev"
Requires-Dist: python-semantic-release>=10.5.3; extra == "dev"
Requires-Dist: pre-commit>=3.0; extra == "dev"
Requires-Dist: types-protobuf<7.0,>6.32; extra == "dev"
Provides-Extra: simple
Requires-Dist: pandas<3.0.0,>=2.0.0; extra == "simple"
Provides-Extra: lint
Requires-Dist: commitlint>=19.0; extra == "lint"
Dynamic: license-file
